pysqlite3/__init__.py
pysqlite3/_sqlite3.cpython-313-x86_64-linux-musl.so
pysqlite3/dbapi2.py
pysqlite3-0.6.0.dist-info/METADATA
pysqlite3-0.6.0.dist-info/WHEEL
pysqlite3-0.6.0.dist-info/top_level.txt
pysqlite3-0.6.0.dist-info/RECORD
pysqlite3-0.6.0.dist-info/licenses/LICENSE
