Metadata-Version: 2.4
Name: pysqlite3
Version: 0.6.0
Summary: DB-API 2.0 interface for Sqlite 3.x
Author-email: Charles Leifer <coleifer@gmail.com>
License-Expression: MIT
Classifier: Programming Language :: Python :: 3
Classifier: Programming Language :: C
Classifier: Topic :: Database :: Database Engines/Servers
Requires-Python: >=3.9
License-File: LICENSE
Dynamic: license-file
